mangowg/DataScraper.py
mangowg/TemplateGeneratorYattag.py
mangowg/mangowg.py
mangowg-0.1.14.dist-info/METADATA
mangowg-0.1.14.dist-info/WHEEL
mangowg-0.1.14.dist-info/entry_points.txt
mangowg-0.1.14.dist-info/RECORD
